{
	"id": "ef58e27d-b434-4bb7-dc57-635524d1a583",
	"name": "Zelo-api",
	"description": "",
	"order": [
		"4765f49d-2d7a-2f6e-f468-7c46dc802954",
		"c255b6cb-2818-a8d6-fc73-3ddea5fee925",
		"3028ba37-3a55-424c-bb92-4548abf4de2a",
		"9ff2fc3e-b40f-5e72-5e52-4d838c09ef13",
		"a36b637a-bb9b-045b-8b7d-f2ffcda3734b",
		"68fe711c-0fd2-8bca-c3cb-fde443804a8b",
		"2efc0b20-6ba8-c99f-5b71-b2e2fce9ddfe",
		"3c818d15-8f64-f7b3-bab3-01806775d516",
		"754be04b-6eb8-1ee5-a0e5-a0b46543c577"
	],
	"folders": [],
	"folders_order": [],
	"timestamp": 1510833498064,
	"owner": "2262042",
	"public": false,
	"requests": [
		{
			"id": "2efc0b20-6ba8-c99f-5b71-b2e2fce9ddfe",
			"headers": "Content-Type: application/json\n",
			"headerData": [
				{
					"key": "Content-Type",
					"value": "application/json",
					"description": "",
					"enabled": true
				}
			],
			"url": "https://zeloapi.herokuapp.com/loyaltycard/balance",
			"queryParams": [],
			"preRequestScript": null,
			"pathVariables": {},
			"pathVariableData": [],
			"method": "POST",
			"data": [],
			"dataMode": "raw",
			"tests": null,
			"currentHelper": "normal",
			"helperAttributes": {},
			"time": 1510840955752,
			"name": "/loyaltycard/balance",
			"description": "",
			"collectionId": "ef58e27d-b434-4bb7-dc57-635524d1a583",
			"responses": [],
			"rawModeData": "{\n\t\"card_id\": \"some value\",\n\t\"document_number\": \"03970157048\",\n\t\"email\": \"some value\"\n}"
		},
		{
			"id": "3028ba37-3a55-424c-bb92-4548abf4de2a",
			"headers": "Content-Type: application/json\n",
			"headerData": [
				{
					"key": "Content-Type",
					"value": "application/json",
					"description": "",
					"enabled": true
				}
			],
			"url": "http://localhost:5000/giftcard/balance",
			"queryParams": [],
			"pathVariables": {},
			"pathVariableData": [],
			"preRequestScript": null,
			"method": "POST",
			"collectionId": "ef58e27d-b434-4bb7-dc57-635524d1a583",
			"data": [],
			"dataMode": "raw",
			"name": "/giftcard/balance",
			"description": "",
			"descriptionFormat": "html",
			"time": 1511198767898,
			"version": 2,
			"responses": [],
			"tests": null,
			"currentHelper": "normal",
			"helperAttributes": {},
			"rawModeData": "{\n\t\"card_id\": \"GC-00001\",\n\t\"email\": \"some value\"\n}"
		},
		{
			"id": "3c818d15-8f64-f7b3-bab3-01806775d516",
			"headers": "Content-Type: application/json\n",
			"headerData": [
				{
					"key": "Content-Type",
					"value": "application/json",
					"description": "",
					"enabled": true
				}
			],
			"url": "https://zeloapi.herokuapp.com/loyaltycard/capture",
			"queryParams": [],
			"preRequestScript": null,
			"pathVariables": {},
			"pathVariableData": [],
			"method": "POST",
			"data": [],
			"dataMode": "raw",
			"tests": null,
			"currentHelper": "normal",
			"helperAttributes": {},
			"time": 1510854403022,
			"name": "/loyaltycard/capture",
			"description": "",
			"collectionId": "ef58e27d-b434-4bb7-dc57-635524d1a583",
			"responses": [],
			"rawModeData": "{\n\t\"order_number\": \"123144123\",\n\t\"card\": {\n\t\t\"card_id\": \"LO-00003\",\n\t\t\"document_number\": \"as\",\n\t\t\"email\": \"some value\"\n\t},\n\t\"value\": 50\n\t\n}"
		},
		{
			"id": "4765f49d-2d7a-2f6e-f468-7c46dc802954",
			"headers": "",
			"headerData": [],
			"url": "https://zeloapi.herokuapp.com/giftcard",
			"queryParams": [],
			"preRequestScript": null,
			"pathVariables": {},
			"pathVariableData": [],
			"method": "GET",
			"data": null,
			"dataMode": "params",
			"tests": null,
			"currentHelper": "normal",
			"helperAttributes": {},
			"time": 1510840898280,
			"name": "/giftcard",
			"description": "",
			"collectionId": "ef58e27d-b434-4bb7-dc57-635524d1a583",
			"responses": []
		},
		{
			"id": "68fe711c-0fd2-8bca-c3cb-fde443804a8b",
			"headers": "Content-Type: application/json\n",
			"headerData": [
				{
					"key": "Content-Type",
					"value": "application/json",
					"description": "",
					"enabled": true
				}
			],
			"url": "https://zeloapi.herokuapp.com/loyaltycard/create",
			"queryParams": [],
			"preRequestScript": null,
			"pathVariables": {},
			"pathVariableData": [],
			"method": "POST",
			"data": [],
			"dataMode": "raw",
			"tests": null,
			"currentHelper": "normal",
			"helperAttributes": {},
			"time": 1510920109989,
			"name": "/loyaltycard/create",
			"description": "",
			"collectionId": "ef58e27d-b434-4bb7-dc57-635524d1a583",
			"responses": [],
			"rawModeData": "{\r\n    \"card_id\": \"LO-00003\",\r\n    \"message\": \"Mensagem cartão fidelidade\",\r\n    \"is_valid\": true,\r\n    \"balance\": \"100\",\r\n    \"email\": \"email@ezcommerce.com.br\",\r\n    \"document_number\": \"12345678910\"\r\n}"
		},
		{
			"id": "754be04b-6eb8-1ee5-a0e5-a0b46543c577",
			"headers": "",
			"headerData": [],
			"url": "https://zeloapi.herokuapp.com/transaction",
			"queryParams": [],
			"pathVariables": {},
			"pathVariableData": [],
			"preRequestScript": null,
			"method": "GET",
			"collectionId": "ef58e27d-b434-4bb7-dc57-635524d1a583",
			"data": null,
			"dataMode": "params",
			"name": "/transaction",
			"description": "",
			"descriptionFormat": "html",
			"time": 1510854439492,
			"version": 2,
			"responses": [],
			"tests": null,
			"currentHelper": "normal",
			"helperAttributes": {}
		},
		{
			"id": "9ff2fc3e-b40f-5e72-5e52-4d838c09ef13",
			"headers": "Content-Type: application/json\n",
			"headerData": [
				{
					"key": "Content-Type",
					"value": "application/json",
					"description": "",
					"enabled": true
				}
			],
			"url": "https://zeloapi.herokuapp.com/giftcard/capture",
			"queryParams": [],
			"preRequestScript": null,
			"pathVariables": {},
			"pathVariableData": [],
			"method": "POST",
			"data": [],
			"dataMode": "raw",
			"tests": null,
			"currentHelper": "normal",
			"helperAttributes": {},
			"time": 1510854519636,
			"name": "/giftcard/capture",
			"description": "",
			"collectionId": "ef58e27d-b434-4bb7-dc57-635524d1a583",
			"responses": [],
			"rawModeData": "{\n\t\"ordernumber\": \"123123123\",\n\t\"cards\": [\n\t\t{\n\t\t\t\"card_id\": \"GC-00005\",\n\t\t\t\"email\": \"email\"\n\t\t},\n\t\t{\n\t\t\t\"card_id\": \"GC-00005\",\n\t\t\t\"email\": \"email\"\n\t\t}\n\t]\n}"
		},
		{
			"id": "a36b637a-bb9b-045b-8b7d-f2ffcda3734b",
			"headers": "",
			"headerData": [],
			"url": "https://zeloapi.herokuapp.com/loyaltycard",
			"queryParams": [],
			"preRequestScript": null,
			"pathVariables": {},
			"pathVariableData": [],
			"method": "GET",
			"data": null,
			"dataMode": "params",
			"tests": null,
			"currentHelper": "normal",
			"helperAttributes": {},
			"time": 1510840944863,
			"name": "/loyaltycard",
			"description": "",
			"collectionId": "ef58e27d-b434-4bb7-dc57-635524d1a583",
			"responses": []
		},
		{
			"id": "c255b6cb-2818-a8d6-fc73-3ddea5fee925",
			"headers": "Content-Type: application/json\n",
			"headerData": [
				{
					"key": "Content-Type",
					"value": "application/json",
					"description": "",
					"enabled": true
				}
			],
			"url": "https://zeloapi.herokuapp.com/giftcard/create",
			"queryParams": [],
			"preRequestScript": null,
			"pathVariables": {},
			"pathVariableData": [],
			"method": "POST",
			"data": [],
			"dataMode": "raw",
			"tests": null,
			"currentHelper": "normal",
			"helperAttributes": {},
			"time": 1510846640617,
			"name": "/giftcard/create",
			"description": "",
			"collectionId": "ef58e27d-b434-4bb7-dc57-635524d1a583",
			"responses": [],
			"rawModeData": "{\r\n    \"card_id\": \"GC-00001\",\r\n    \"message\": \"Mensagem cartão presente\",\r\n    \"balance\": \"100.50\",\r\n    \"email\": \"email@ezcommerce.com.br\"\r\n}"
		}
	]
}